[
  {
    "id": 1,
    "nombre": "Cheesecake",
    "descripcion": "Nuestro postre estrella: cremoso, suave y hecho en casa.",
    "precio": 3.00,
    "imagen_url": "src/imagenes/menu/chesscake1.jpg"
  },
  {
    "id": 2,
    "nombre": "Toasted butter cookies",
    "descripcion": "Crujientes galletas de mantequilla, perfectas para el café.",
    "precio": 1.50,
    "imagen_url": "src/imagenes/menu/cookies.jpg"
  },
  {
    "id": 3,
    "nombre": "Pie de limón",
    "descripcion": "Perfecto balance entre dulce y ácido, con merengue flameado.",
    "precio": 3.50,
    "imagen_url": "src/imagenes/menu/pie_limon.jpg"
  },
  {
    "id": 4,
    "nombre": "Profiteroles",
    "descripcion": "Rellenos de crema pastelera y bañados en azúcar glas.",
    "precio": 2.50,
    "imagen_url": "src/imagenes/menu/profiteroles.jpg"
  },
  {
    "id": 5,
    "nombre": "Spicy Tuna",
    "descripcion": "Atún con un toque picante y vegetales frescos.",
    "precio": 2.50,
    "imagen_url": "src/imagenes/menu/atun.jpg"
  },
  {
    "id": 6,
    "nombre": "Muffin de jamón y queso",
    "descripcion": "Ideal para empezar el día o una merienda rápida.",
    "precio": 2.00,
    "imagen_url": "src/imagenes/menu/sanduche_jamon.jpg"
  },
    {
    "id": 7,
    "nombre": "Boom de jamón",
    "descripcion": "El clásico de jamón y queso, caliente y irresistible.",
    "precio": 3.00,
    "imagen_url": "src/imagenes/menu/muffin_jq.jpg"
  },
  {
    "id": 8,
    "nombre": "Café americano",
    "descripcion": "El clásico vigorizante, con granos de origen local.",
    "precio": 1.00,
    "imagen_url": "src/imagenes/menu/cafe_a.png"
  },
  {
    "id": 9,
    "nombre": "Capuccino",
    "descripcion": "Receta especial de la casa con espuma suave y arte latte.",
    "precio": 3.00,
    "imagen_url": "src/imagenes/menu/c_capuccino.jpg"
  }

]